fhepy/main.py
fhepy-0.1.0.dist-info/METADATA
fhepy-0.1.0.dist-info/WHEEL
fhepy-0.1.0.dist-info/RECORD
